celcomen/__init__.py
celcomen/.ipynb_checkpoints/__init__-checkpoint.py
celcomen/datareaders/datareader.py
celcomen/datareaders/.ipynb_checkpoints/datareader-checkpoint.py
celcomen/models/__init__.py
celcomen/models/celcomen.py
celcomen/models/simcomen.py
celcomen/models/.ipynb_checkpoints/__init__-checkpoint.py
celcomen/models/.ipynb_checkpoints/celcomen-checkpoint.py
celcomen/models/.ipynb_checkpoints/simcomen-checkpoint.py
celcomen/training_plan/train.py
celcomen/training_plan/.ipynb_checkpoints/train-checkpoint.py
celcomen/utils/__init__.py
celcomen/utils/helpers.py
celcomen/utils/.ipynb_checkpoints/__init__-checkpoint.py
celcomen/utils/.ipynb_checkpoints/helpers-checkpoint.py
celcomen-0.0.1.dist-info/WHEEL
celcomen-0.0.1.dist-info/METADATA
celcomen-0.0.1.dist-info/RECORD
